{
    "pageid": 1456781,
    "ns": 0,
    "title": "Q1519617",
    "lastrevid": 1330559502,
    "modified": "2020-12-29T02:57:15Z",
    "type": "item",
    "id": "Q1519617",
    "labels": {
        "ru": {
            "language": "ru",
            "value": "Полосатый листолаз"
        },
        "fr": {
            "language": "fr",
            "value": "Phyllobates vittatus"
        },
        "en": {
            "language": "en",
            "value": "Golfodulcean poison frog"
        },
        "nl": {
            "language": "nl",
            "value": "Gestreepte pijlgifkikker"
        },
        "vi": {
            "language": "vi",
            "value": "Phyllobates vittatus"
        },
        "de": {
            "language": "de",
            "value": "Gestreifter Blattsteiger"
        },
        "pl": {
            "language": "pl",
            "value": "Liściołaz paskowany"
        },
        "ceb": {
            "language": "ceb",
            "value": "Phyllobates vittatus"
        },
        "war": {
            "language": "war",
            "value": "Phyllobates vittatus"
        },
        "es": {
            "language": "es",
            "value": "Phyllobates vittatus"
        },
        "it": {
            "language": "it",
            "value": "Phyllobates vittatus"
        },
        "la": {
            "language": "la",
            "value": "Phyllobates vittatus"
        },
        "sv": {
            "language": "sv",
            "value": "Phyllobates vittatus"
        },
        "eu": {
            "language": "eu",
            "value": "Phyllobates vittatus"
        },
        "bg": {
            "language": "bg",
            "value": "Phyllobates vittatus"
        },
        "ia": {
            "language": "ia",
            "value": "Phyllobates vittatus"
        },
        "uk": {
            "language": "uk",
            "value": "Phyllobates vittatus"
        },
        "ast": {
            "language": "ast",
            "value": "Phyllobates vittatus"
        },
        "fi": {
            "language": "fi",
            "value": "Golfodulcenmyrkkysammakko"
        },
        "ga": {
            "language": "ga",
            "value": "Phyllobates vittatus"
        },
        "ro": {
            "language": "ro",
            "value": "Phyllobates vittatus"
        },
        "pt": {
            "language": "pt",
            "value": "Phyllobates vittatus"
        },
        "nv": {
            "language": "nv",
            "value": "Chʼał kʼaasdáhí bijáád yistłʼinígíí"
        },
        "sq": {
            "language": "sq",
            "value": "Phyllobates vittatus"
        }
    },
    "descriptions": {
        "de": {
            "language": "de",
            "value": "Art der Gattung Blattsteiger (Phyllobates)"
        },
        "en": {
            "language": "en",
            "value": "species of amphibian"
        },
        "bg": {
            "language": "bg",
            "value": "вид земноводно"
        },
        "nl": {
            "language": "nl",
            "value": "kikker uit de familie pijlgifkikkers"
        },
        "ar": {
            "language": "ar",
            "value": "نوع من البرمائيات"
        },
        "zh": {
            "language": "zh",
            "value": "两栖动物物种"
        },
        "fr": {
            "language": "fr",
            "value": "espèce d'amphibiens"
        },
        "pt": {
            "language": "pt",
            "value": "espécie de anfíbio"
        },
        "es": {
            "language": "es",
            "value": "especie de anfibio"
        },
        "ca": {
            "language": "ca",
            "value": "espècie d'amfibi"
        },
        "bn": {
            "language": "bn",
            "value": "উভচর প্রাণীর প্রজাতি"
        },
        "he": {
            "language": "he",
            "value": "מין של דו-חיים"
        },
        "ro": {
            "language": "ro",
            "value": "specie de amfibieni"
        },
        "sq": {
            "language": "sq",
            "value": "lloj i amfibeve"
        },
        "cs": {
            "language": "cs",
            "value": "druh obojživelníka"
        },
        "io": {
            "language": "io",
            "value": "speco di amfibio"
        },
        "uk": {
            "language": "uk",
            "value": "вид земноводних"
        },
        "ast": {
            "language": "ast",
            "value": "especie d'anfibiu"
        },
        "ga": {
            "language": "ga",
            "value": "speiceas amfaibiach"
        }
    },
    "aliases": {
        "ru": [
            {
                "language": "ru",
                "value": "Phyllobates vittatus"
            }
        ],
        "fr": [
            {
                "language": "fr",
                "value": "Dendrobates tinctorius vittatus"
            }
        ],
        "nl": [
            {
                "language": "nl",
                "value": "Golfo Dulce gestreepte pijlgifkikker"
            },
            {
                "language": "nl",
                "value": "Phyllobates vittatus"
            }
        ],
        "de": [
            {
                "language": "de",
                "value": "Phyllobates vittatus"
            }
        ],
        "pl": [
            {
                "language": "pl",
                "value": "Phyllobates vittatus"
            }
        ],
        "en": [
            {
                "language": "en",
                "value": "Phyllobates vittatus"
            }
        ]
    },
    "claims": {
        "P105": [
            {
                "mainsnak": {
                    "snaktype": "value",
                    "property": "P105",
                    "hash": "aebf3611b23ed90c7c0fc80f6cd1cb7be110ea59",
                    "datavalue": {
                        "value": {
                            "entity-type": "item",
                            "numeric-id": 7432,
                            "id": "Q7432"
                        },
                        "type": "wikibase-entityid"
                    },
                    "datatype": "wikibase-item"
                },
                "type": "statement",
                "id": "q1519617$F6AF1E9B-2384-4212-B5C3-44269A7B994F",
                "rank": "normal",
                "references": [
                    {
                        "hash": "af83058a4c0e272266fd39bb440ff3fd391f21b5",
                        "snaks": {
                            "P248": [
                                {
                                    "snaktype": "value",
                                    "property": "P248",
                                    "hash": "c26dbcef1202a7d198982ed24f6ea69b704f95fe",
                                    "datavalue": {
                                        "value": {
                                            "entity-type": "item",
                                            "numeric-id": 82575,
                                            "id": "Q82575"
                                        },
                                        "type": "wikibase-entityid"
                                    },
                                    "datatype": "wikibase-item"
                                }
                            ],
                            "P577": [
                                {
                                    "snaktype": "value",
                                    "property": "P577",
                                    "hash": "2fa81cb6b701d9750cc624c03e5937d6c80a5d09",
                                    "datavalue": {
                                        "value": {
                                            "time": "+2005-03-02T00:00:00Z",
                                            "timezone": 0,
                                            "before": 0,
                                            "after": 0,
                                            "precision": 11,
                                            "calendarmodel": "http://www.wikidata.org/entity/Q1985727"
                                        },
                                        "type": "time"
                                    },
                                    "datatype": "time"
                                }
                            ],
                            "P813": [
                                {
                                    "snaktype": "value",
                                    "property": "P813",
                                    "hash": "96dfb8481e184edb40553947f8fe08ce080f1553",
                                    "datavalue": {
                                        "value": {
                                            "time": "+2013-09-19T00:00:00Z",
                                            "timezone": 0,
                                            "before": 0,
                                            "after": 0,
                                            "precision": 11,
                                            "calendarmodel": "http://www.wikidata.org/entity/Q1985727"
                                        },
                                        "type": "time"
                                    },
                                    "datatype": "time"
                                }
                            ]
                        },
                        "snaks-order": [
                            "P248",
                            "P577",
                            "P813"
                        ]
                    }
                ]
            }
        ],
        "P141": [
            {
                "mainsnak": {
                    "snaktype": "value",
                    "property": "P141",
                    "hash": "80026ea5b2066a2538fee5c0897b459bb6770689",
                    "datavalue": {
                        "value": {
                            "entity-type": "item",
                            "numeric-id": 278113,
                            "id": "Q278113"
                        },
                        "type": "wikibase-entityid"
                    },
                    "datatype": "wikibase-item"
                },
                "type": "statement",
                "id": "q1519617$1F361293-6D8D-44E8-A3E9-18E3DCEF56AD",
                "rank": "normal",
                "references": [
                    {
                        "hash": "99fc9e29b065878e62915938b0151fafe01f32ca",
                        "snaks": {
                            "P248": [
                                {
                                    "snaktype": "value",
                                    "property": "P248",
                                    "hash": "744bc312f33e8ae7ea0bc4910a0314a610cc3e72",
                                    "datavalue": {
                                        "value": {
                                            "entity-type": "item",
                                            "numeric-id": 104368521,
                                            "id": "Q104368521"
                                        },
                                        "type": "wikibase-entityid"
                                    },
                                    "datatype": "wikibase-item"
                                }
                            ],
                            "P627": [
                                {
                                    "snaktype": "value",
                                    "property": "P627",
                                    "hash": "1ddff4551508c9cd4615b64c2ab183248382449e",
                                    "datavalue": {
                                        "value": "55265",
                                        "type": "string"
                                    },
                                    "datatype": "string"
                                }
                            ],
                            "P813": [
                                {
                                    "snaktype": "value",
                                    "property": "P813",
                                    "hash": "7c19ebf0632551d9c263bed2b9df22105e159c64",
                                    "datavalue": {
                                        "value": {
                                            "time": "+2020-12-29T00:00:00Z",
                                            "timezone": 0,
                                            "before": 0,
                                            "after": 0,
                                            "precision": 11,
                                            "calendarmodel": "http://www.wikidata.org/entity/Q1985727"
                                        },
                                        "type": "time"
                                    },
                                    "datatype": "time"
                                }
                            ]
                        },
                        "snaks-order": [
                            "P248",
                            "P627",
                            "P813"
                        ]
                    }
                ]
            }
        ],
        "P225": [
            {
                "mainsnak": {
                    "snaktype": "value",
                    "property": "P225",
                    "hash": "52b03423390a89d54385cee4a5337dc809c399d7",
                    "datavalue": {
                        "value": "Phyllobates vittatus",
                        "type": "string"
                    },
                    "datatype": "string"
                },
                "type": "statement",
                "qualifiers": {
                    "P405": [
                        {
                            "snaktype": "value",
                            "property": "P405",
                            "hash": "e5d391cc9cbf5eb05d2bb6d314f64529d9c115ff",
                            "datavalue": {
                                "value": {
                                    "entity-type": "item",
                                    "numeric-id": 298933,
                                    "id": "Q298933"
                                },
                                "type": "wikibase-entityid"
                            },
                            "datatype": "wikibase-item"
                        }
                    ],
                    "P574": [
                        {
                            "snaktype": "value",
                            "property": "P574",
                            "hash": "3e4ba0c6756cf543f9799fc00c856d66ff229f20",
                            "datavalue": {
                                "value": {
                                    "time": "+1893-01-01T00:00:00Z",
                                    "timezone": 0,
                                    "before": 0,
                                    "after": 0,
                                    "precision": 9,
                                    "calendarmodel": "http://www.wikidata.org/entity/Q1985727"
                                },
                                "type": "time"
                            },
                            "datatype": "time"
                        }
                    ]
                },
                "qualifiers-order": [
                    "P405",
                    "P574"
                ],
                "id": "q1519617$05ED5730-441C-495D-BCDB-7312C5558CEC",
                "rank": "normal",
                "references": [
                    {
                        "hash": "af83058a4c0e272266fd39bb440ff3fd391f21b5",
                        "snaks": {
                            "P248": [
                                {
                                    "snaktype": "value",
                                    "property": "P248",
                                    "hash": "c26dbcef1202a7d198982ed24f6ea69b704f95fe",
                                    "datavalue": {
                                        "value": {
                                            "entity-type": "item",
                                            "numeric-id": 82575,
                                            "id": "Q82575"
                                        },
                                        "type": "wikibase-entityid"
                                    },
                                    "datatype": "wikibase-item"
                                }
                            ],
                            "P577": [
                                {
                                    "snaktype": "value",
                                    "property": "P577",
                                    "hash": "2fa81cb6b701d9750cc624c03e5937d6c80a5d09",
                                    "datavalue": {
                                        "value": {
                                            "time": "+2005-03-02T00:00:00Z",
                                            "timezone": 0,
                                            "before": 0,
                                            "after": 0,
                                            "precision": 11,
                                            "calendarmodel": "http://www.wikidata.org/entity/Q1985727"
                                        },
                                        "type": "time"
                                    },
                                    "datatype": "time"
                                }
                            ],
                            "P813": [
                                {
                                    "snaktype": "value",
                                    "property": "P813",
                                    "hash": "96dfb8481e184edb40553947f8fe08ce080f1553",
                                    "datavalue": {
                                        "value": {
                                            "time": "+2013-09-19T00:00:00Z",
                                            "timezone": 0,
                                            "before": 0,
                                            "after": 0,
                                            "precision": 11,
                                            "calendarmodel": "http://www.wikidata.org/entity/Q1985727"
                                        },
                                        "type": "time"
                                    },
                                    "datatype": "time"
                                }
                            ]
                        },
                        "snaks-order": [
                            "P248",
                            "P577",
                            "P813"
                        ]
                    }
                ]
            }
        ],
        "P373": [
            {
                "mainsnak": {
                    "snaktype": "value",
                    "property": "P373",
                    "hash": "22fc3c1456ea24bb12022313b0b8443f5717fd73",
                    "datavalue": {
                        "value": "Phyllobates vittatus",
                        "type": "string"
                    },
                    "datatype": "string"
                },
                "type": "statement",
                "id": "q1519617$BFEAE137-A9F5-41C5-91E2-857B16AEA4E6",
                "rank": "normal"
            }
        ],
        "P18": [
            {
                "mainsnak": {
                    "snaktype": "value",
                    "property": "P18",
                    "hash": "ea5b305a20a5454552402f9821405f30448b2bc5",
                    "datavalue": {
                        "value": "Dählhölzli - Gestreifter Blattsteiger 1.jpg",
                        "type": "string"
                    },
                    "datatype": "commonsMedia"
                },
                "type": "statement",
                "id": "q1519617$DF2FC5CC-DEDD-409C-B50D-CE84A258E1BA",
                "rank": "normal"
            }
        ],
        "P171": [
            {
                "mainsnak": {
                    "snaktype": "value",
                    "property": "P171",
                    "hash": "679a81929f6233da4c84783c51e046f491784d4d",
                    "datavalue": {
                        "value": {
                            "entity-type": "item",
                            "numeric-id": 882284,
                            "id": "Q882284"
                        },
                        "type": "wikibase-entityid"
                    },
                    "datatype": "wikibase-item"
                },
                "type": "statement",
                "id": "Q1519617$CBC34D83-DDE9-43B4-972D-BBD4B4379D72",
                "rank": "normal",
                "references": [
                    {
                        "hash": "af83058a4c0e272266fd39bb440ff3fd391f21b5",
                        "snaks": {
                            "P248": [
                                {
                                    "snaktype": "value",
                                    "property": "P248",
                                    "hash": "c26dbcef1202a7d198982ed24f6ea69b704f95fe",
                                    "datavalue": {
                                        "value": {
                                            "entity-type": "item",
                                            "numeric-id": 82575,
                                            "id": "Q82575"
                                        },
                                        "type": "wikibase-entityid"
                                    },
                                    "datatype": "wikibase-item"
                                }
                            ],
                            "P577": [
                                {
                                    "snaktype": "value",
                                    "property": "P577",
                                    "hash": "2fa81cb6b701d9750cc624c03e5937d6c80a5d09",
                                    "datavalue": {
                                        "value": {
                                            "time": "+2005-03-02T00:00:00Z",
                                            "timezone": 0,
                                            "before": 0,
                                            "after": 0,
                                            "precision": 11,
                                            "calendarmodel": "http://www.wikidata.org/entity/Q1985727"
                                        },
                                        "type": "time"
                                    },
                                    "datatype": "time"
                                }
                            ],
                            "P813": [
                                {
                                    "snaktype": "value",
                                    "property": "P813",
                                    "hash": "96dfb8481e184edb40553947f8fe08ce080f1553",
                                    "datavalue": {
                                        "value": {
                                            "time": "+2013-09-19T00:00:00Z",
                                            "timezone": 0,
                                            "before": 0,
                                            "after": 0,
                                            "precision": 11,
                                            "calendarmodel": "http://www.wikidata.org/entity/Q1985727"
                                        },
                                        "type": "time"
                                    },
                                    "datatype": "time"
                                }
                            ]
                        },
                        "snaks-order": [
                            "P248",
                            "P577",
                            "P813"
                        ]
                    }
                ]
            }
        ],
        "P815": [
            {
                "mainsnak": {
                    "snaktype": "value",
                    "property": "P815",
                    "hash": "09a12e7dec6cbe8e2545b5411d87ad529c4b0c7d",
                    "datavalue": {
                        "value": "662322",
                        "type": "string"
                    },
                    "datatype": "external-id"
                },
                "type": "statement",
                "id": "Q1519617$36949AF6-9D29-471E-9EF3-6F2B4F207ABB",
                "rank": "normal",
                "references": [
                    {
                        "hash": "89f687563ac6295eb241537b9b5397819d8045bb",
                        "snaks": {
                            "P248": [
                                {
                                    "snaktype": "value",
                                    "property": "P248",
                                    "hash": "c26dbcef1202a7d198982ed24f6ea69b704f95fe",
                                    "datavalue": {
                                        "value": {
                                            "entity-type": "item",
                                            "numeric-id": 82575,
                                            "id": "Q82575"
                                        },
                                        "type": "wikibase-entityid"
                                    },
                                    "datatype": "wikibase-item"
                                }
                            ],
                            "P813": [
                                {
                                    "snaktype": "value",
                                    "property": "P813",
                                    "hash": "8e650534c851097ce7c63b729fbc76a1420abe78",
                                    "datavalue": {
                                        "value": {
                                            "time": "+2014-11-08T00:00:00Z",
                                            "timezone": 0,
                                            "before": 0,
                                            "after": 0,
                                            "precision": 11,
                                            "calendarmodel": "http://www.wikidata.org/entity/Q1985727"
                                        },
                                        "type": "time"
                                    },
                                    "datatype": "time"
                                }
                            ]
                        },
                        "snaks-order": [
                            "P248",
                            "P813"
                        ]
                    }
                ]
            }
        ],
        "P685": [
            {
                "mainsnak": {
                    "snaktype": "value",
                    "property": "P685",
                    "hash": "8b2b3fd2132774cddcaeba2a2864abe6c8bbf018",
                    "datavalue": {
                        "value": "51963",
                        "type": "string"
                    },
                    "datatype": "external-id"
                },
                "type": "statement",
                "id": "Q1519617$4F1E0C85-6785-4681-BFEA-A91E7692C16D",
                "rank": "normal",
                "references": [
                    {
                        "hash": "fc85b2719ff944c3b69c3c5e986f2c3012fb53f3",
                        "snaks": {
                            "P248": [
                                {
                                    "snaktype": "value",
                                    "property": "P248",
                                    "hash": "1851bc60ddfbcf6f76bd45aa7124fc0d5857a379",
                                    "datavalue": {
                                        "value": {
                                            "entity-type": "item",
                                            "numeric-id": 13711410,
                                            "id": "Q13711410"
                                        },
                                        "type": "wikibase-entityid"
                                    },
                                    "datatype": "wikibase-item"
                                }
                            ],
                            "P813": [
                                {
                                    "snaktype": "value",
                                    "property": "P813",
                                    "hash": "f6f141c5bcd20de38857452090ff2657ec712e5e",
                                    "datavalue": {
                                        "value": {
                                            "time": "+2015-11-12T00:00:00Z",
                                            "timezone": 0,
                                            "before": 0,
                                            "after": 0,
                                            "precision": 11,
                                            "calendarmodel": "http://www.wikidata.org/entity/Q1985727"
                                        },
                                        "type": "time"
                                    },
                                    "datatype": "time"
                                }
                            ]
                        },
                        "snaks-order": [
                            "P248",
                            "P813"
                        ]
                    }
                ]
            }
        ],
        "P31": [
            {
                "mainsnak": {
                    "snaktype": "value",
                    "property": "P31",
                    "hash": "06629d890d7ab0ff85c403d8aadf57ce9809c01f",
                    "datavalue": {
                        "value": {
                            "entity-type": "item",
                            "numeric-id": 16521,
                            "id": "Q16521"
                        },
                        "type": "wikibase-entityid"
                    },
                    "datatype": "wikibase-item"
                },
                "type": "statement",
                "id": "Q1519617$27F55708-9123-42AB-862B-0CBDBE989556",
                "rank": "normal"
            }
        ],
        "P646": [
            {
                "mainsnak": {
                    "snaktype": "value",
                    "property": "P646",
                    "hash": "d01ff8dbdc5103e519c70f69d2119cd2dab39dd3",
                    "datavalue": {
                        "value": "/m/02w1jr5",
                        "type": "string"
                    },
                    "datatype": "external-id"
                },
                "type": "statement",
                "id": "Q1519617$AB16ECD4-F99D-4081-9861-75CAF6E2D4E0",
                "rank": "normal",
                "references": [
                    {
                        "hash": "2b00cb481cddcac7623114367489b5c194901c4a",
                        "snaks": {
                            "P248": [
                                {
                                    "snaktype": "value",
                                    "property": "P248",
                                    "hash": "a94b740202b097dd33355e0e6c00e54b9395e5e0",
                                    "datavalue": {
                                        "value": {
                                            "entity-type": "item",
                                            "numeric-id": 15241312,
                                            "id": "Q15241312"
                                        },
                                        "type": "wikibase-entityid"
                                    },
                                    "datatype": "wikibase-item"
                                }
                            ],
                            "P577": [
                                {
                                    "snaktype": "value",
                                    "property": "P577",
                                    "hash": "fde79ecb015112d2f29229ccc1ec514ed3e71fa2",
                                    "datavalue": {
                                        "value": {
                                            "time": "+2013-10-28T00:00:00Z",
                                            "timezone": 0,
                                            "before": 0,
                                            "after": 0,
                                            "precision": 11,
                                            "calendarmodel": "http://www.wikidata.org/entity/Q1985727"
                                        },
                                        "type": "time"
                                    },
                                    "datatype": "time"
                                }
                            ]
                        },
                        "snaks-order": [
                            "P248",
                            "P577"
                        ]
                    }
                ]
            }
        ],
        "P830": [
            {
                "mainsnak": {
                    "snaktype": "value",
                    "property": "P830",
                    "hash": "f97f81fb855947d5eafd11532c45f0edf697a937",
                    "datavalue": {
                        "value": "1019162",
                        "type": "string"
                    },
                    "datatype": "external-id"
                },
                "type": "statement",
                "id": "Q1519617$40B4AF1E-3484-448A-BD4D-09D799A5DDDA",
                "rank": "normal",
                "references": [
                    {
                        "hash": "4e6a4543025cd3fc2a830bc6a7a83d94f32979a0",
                        "snaks": {
                            "P248": [
                                {
                                    "snaktype": "value",
                                    "property": "P248",
                                    "hash": "6e81987ab11fb1740bd862639411d0700be3b22c",
                                    "datavalue": {
                                        "value": {
                                            "entity-type": "item",
                                            "numeric-id": 82486,
                                            "id": "Q82486"
                                        },
                                        "type": "wikibase-entityid"
                                    },
                                    "datatype": "wikibase-item"
                                }
                            ],
                            "P813": [
                                {
                                    "snaktype": "value",
                                    "property": "P813",
                                    "hash": "903780101971011c580ceae0847bb5a99d5472b0",
                                    "datavalue": {
                                        "value": {
                                            "time": "+2014-10-31T00:00:00Z",
                                            "timezone": 0,
                                            "before": 0,
                                            "after": 0,
                                            "precision": 11,
                                            "calendarmodel": "http://www.wikidata.org/entity/Q1985727"
                                        },
                                        "type": "time"
                                    },
                                    "datatype": "time"
                                }
                            ]
                        },
                        "snaks-order": [
                            "P248",
                            "P813"
                        ]
                    }
                ]
            }
        ],
        "P846": [
            {
                "mainsnak": {
                    "snaktype": "value",
                    "property": "P846",
                    "hash": "46a831e4ca777202620e5160198f40e20a7f66ff",
                    "datavalue": {
                        "value": "5218018",
                        "type": "string"
                    },
                    "datatype": "external-id"
                },
                "type": "statement",
                "id": "Q1519617$A50C3877-5C91-4A52-AB28-92BD05FD89FD",
                "rank": "normal",
                "references": [
                    {
                        "hash": "b6f27647ecb2b73827944a8e51c156c9b8530a1a",
                        "snaks": {
                            "P248": [
                                {
                                    "snaktype": "value",
                                    "property": "P248",
                                    "hash": "dbb8dd1efbe0158a5227213bd628eeac27a1da65",
                                    "datavalue": {
                                        "value": {
                                            "entity-type": "item",
                                            "numeric-id": 1531570,
                                            "id": "Q1531570"
                                        },
                                        "type": "wikibase-entityid"
                                    },
                                    "datatype": "wikibase-item"
                                }
                            ],
                            "P813": [
                                {
                                    "snaktype": "value",
                                    "property": "P813",
                                    "hash": "ff8ed4cd50710617fae536eb572d7ed1bc6669e7",
                                    "datavalue": {
                                        "value": {
                                            "time": "+2015-05-17T00:00:00Z",
                                            "timezone": 0,
                                            "before": 0,
                                            "after": 0,
                                            "precision": 11,
                                            "calendarmodel": "http://www.wikidata.org/entity/Q1985727"
                                        },
                                        "type": "time"
                                    },
                                    "datatype": "time"
                                }
                            ]
                        },
                        "snaks-order": [
                            "P248",
                            "P813"
                        ]
                    }
                ]
            }
        ],
        "P2040": [
            {
                "mainsnak": {
                    "snaktype": "value",
                    "property": "P2040",
                    "hash": "eb667cf2ae9f42816ef1a8bd282b77aba0c72a49",
                    "datavalue": {
                        "value": "6947",
                        "type": "string"
                    },
                    "datatype": "external-id"
                },
                "type": "statement",
                "id": "Q1519617$614270C0-732A-42B4-B72D-3B2DC5EA6DF9",
                "rank": "normal",
                "references": [
                    {
                        "hash": "348b5187938d682071c94e22f1b30659af715dc7",
                        "snaks": {
                            "P248": [
                                {
                                    "snaktype": "value",
                                    "property": "P248",
                                    "hash": "213dc0d84ed983cbb28466ebb0c45bf8b0730ea2",
                                    "datavalue": {
                                        "value": {
                                            "entity-type": "item",
                                            "numeric-id": 20962955,
                                            "id": "Q20962955"
                                        },
                                        "type": "wikibase-entityid"
                                    },
                                    "datatype": "wikibase-item"
                                }
                            ],
                            "P813": [
                                {
                                    "snaktype": "value",
                                    "property": "P813",
                                    "hash": "3d2c713dec9143721ae196af88fee0fde5ae20f2",
                                    "datavalue": {
                                        "value": {
                                            "time": "+2015-09-10T00:00:00Z",
                                            "timezone": 0,
                                            "before": 0,
                                            "after": 0,
                                            "precision": 11,
                                            "calendarmodel": "http://www.wikidata.org/entity/Q1985727"
                                        },
                                        "type": "time"
                                    },
                                    "datatype": "time"
                                }
                            ]
                        },
                        "snaks-order": [
                            "P248",
                            "P813"
                        ]
                    }
                ]
            }
        ],
        "P935": [
            {
                "mainsnak": {
                    "snaktype": "value",
                    "property": "P935",
                    "hash": "7ba111d0f673ff24a34a028590eb8b7a7bcb2b51",
                    "datavalue": {
                        "value": "Phyllobates vittatus",
                        "type": "string"
                    },
                    "datatype": "string"
                },
                "type": "statement",
                "id": "Q1519617$AB1DDF3A-3033-4CE4-9224-EF5231306817",
                "rank": "normal"
            }
        ],
        "P1843": [
            {
                "mainsnak": {
                    "snaktype": "value",
                    "property": "P1843",
                    "hash": "579d936595934bdfd2d16093ad9f002020eb3812",
                    "datavalue": {
                        "value": {
                            "text": "Golfodulcean poison frog",
                            "language": "en"
                        },
                        "type": "monolingualtext"
                    },
                    "datatype": "monolingualtext"
                },
                "type": "statement",
                "id": "Q1519617$4BA4C552-5E0E-4B65-929C-BF91F17DC822",
                "rank": "normal",
                "references": [
                    {
                        "hash": "e320bd743dc36820f2627d6ef9d8e5cbbec69521",
                        "snaks": {
                            "P248": [
                                {
                                    "snaktype": "value",
                                    "property": "P248",
                                    "hash": "158cddada2d76da9ecb2072e793c1ce99dbcb169",
                                    "datavalue": {
                                        "value": {
                                            "entity-type": "item",
                                            "numeric-id": 433276,
                                            "id": "Q433276"
                                        },
                                        "type": "wikibase-entityid"
                                    },
                                    "datatype": "wikibase-item"
                                }
                            ]
                        },
                        "snaks-order": [
                            "P248"
                        ]
                    }
                ]
            },
            {
                "mainsnak": {
                    "snaktype": "value",
                    "property": "P1843",
                    "hash": "d726523d7ad1c5a6f61c9ab7e2971375e085610a",
                    "datavalue": {
                        "value": {
                            "text": "Golfodulcean Poison-arrow Frog",
                            "language": "en"
                        },
                        "type": "monolingualtext"
                    },
                    "datatype": "monolingualtext"
                },
                "type": "statement",
                "id": "Q1519617$BFCEB6F2-6542-439E-A021-6EFAD5A43662",
                "rank": "normal",
                "references": [
                    {
                        "hash": "eada84c58a38325085267509899037535799e978",
                        "snaks": {
                            "P248": [
                                {
                                    "snaktype": "value",
                                    "property": "P248",
                                    "hash": "ba14d022d7e0c8b74595e7b8aaa1bc2451dd806a",
                                    "datavalue": {
                                        "value": {
                                            "entity-type": "item",
                                            "numeric-id": 32059,
                                            "id": "Q32059"
                                        },
                                        "type": "wikibase-entityid"
                                    },
                                    "datatype": "wikibase-item"
                                }
                            ],
                            "P813": [
                                {
                                    "snaktype": "value",
                                    "property": "P813",
                                    "hash": "3e51c3c32949f8a45f2c3331f55ea6ae68ecf3fe",
                                    "datavalue": {
                                        "value": {
                                            "time": "+2016-10-21T00:00:00Z",
                                            "timezone": 0,
                                            "before": 0,
                                            "after": 0,
                                            "precision": 11,
                                            "calendarmodel": "http://www.wikidata.org/entity/Q1985727"
                                        },
                                        "type": "time"
                                    },
                                    "datatype": "time"
                                }
                            ]
                        },
                        "snaks-order": [
                            "P248",
                            "P813"
                        ]
                    }
                ]
            },
            {
                "mainsnak": {
                    "snaktype": "value",
                    "property": "P1843",
                    "hash": "fea43d79c0cff08fddedebefbf226817b549600e",
                    "datavalue": {
                        "value": {
                            "text": "Golfodulcean Poison Frog",
                            "language": "en"
                        },
                        "type": "monolingualtext"
                    },
                    "datatype": "monolingualtext"
                },
                "type": "statement",
                "id": "Q1519617$9963EEC4-C34C-4C4C-B6FC-31587DD19388",
                "rank": "normal",
                "references": [
                    {
                        "hash": "eada84c58a38325085267509899037535799e978",
                        "snaks": {
                            "P248": [
                                {
                                    "snaktype": "value",
                                    "property": "P248",
                                    "hash": "ba14d022d7e0c8b74595e7b8aaa1bc2451dd806a",
                                    "datavalue": {
                                        "value": {
                                            "entity-type": "item",
                                            "numeric-id": 32059,
                                            "id": "Q32059"
                                        },
                                        "type": "wikibase-entityid"
                                    },
                                    "datatype": "wikibase-item"
                                }
                            ],
                            "P813": [
                                {
                                    "snaktype": "value",
                                    "property": "P813",
                                    "hash": "3e51c3c32949f8a45f2c3331f55ea6ae68ecf3fe",
                                    "datavalue": {
                                        "value": {
                                            "time": "+2016-10-21T00:00:00Z",
                                            "timezone": 0,
                                            "before": 0,
                                            "after": 0,
                                            "precision": 11,
                                            "calendarmodel": "http://www.wikidata.org/entity/Q1985727"
                                        },
                                        "type": "time"
                                    },
                                    "datatype": "time"
                                }
                            ]
                        },
                        "snaks-order": [
                            "P248",
                            "P813"
                        ]
                    }
                ]
            }
        ],
        "P627": [
            {
                "mainsnak": {
                    "snaktype": "value",
                    "property": "P627",
                    "hash": "1ddff4551508c9cd4615b64c2ab183248382449e",
                    "datavalue": {
                        "value": "55265",
                        "type": "string"
                    },
                    "datatype": "string"
                },
                "type": "statement",
                "id": "Q1519617$A1F5825A-D830-4425-93E4-0EDDC8BA6F79",
                "rank": "normal",
                "references": [
                    {
                        "hash": "182efbdb9110d036ca433f3b49bd3a1ae312858b",
                        "snaks": {
                            "P248": [
                                {
                                    "snaktype": "value",
                                    "property": "P248",
                                    "hash": "ba14d022d7e0c8b74595e7b8aaa1bc2451dd806a",
                                    "datavalue": {
                                        "value": {
                                            "entity-type": "item",
                                            "numeric-id": 32059,
                                            "id": "Q32059"
                                        },
                                        "type": "wikibase-entityid"
                                    },
                                    "datatype": "wikibase-item"
                                }
                            ],
                            "P813": [
                                {
                                    "snaktype": "value",
                                    "property": "P813",
                                    "hash": "8c1c5174f4811115ea8a0def725fdc074c2ef036",
                                    "datavalue": {
                                        "value": {
                                            "time": "+2016-07-10T00:00:00Z",
                                            "timezone": 0,
                                            "before": 0,
                                            "after": 0,
                                            "precision": 11,
                                            "calendarmodel": "http://www.wikidata.org/entity/Q1985727"
                                        },
                                        "type": "time"
                                    },
                                    "datatype": "time"
                                }
                            ]
                        },
                        "snaks-order": [
                            "P248",
                            "P813"
                        ]
                    }
                ]
            }
        ],
        "P2833": [
            {
                "mainsnak": {
                    "snaktype": "value",
                    "property": "P2833",
                    "hash": "99f2253cc1d7e020b8767e447a60eaf2d0a05ecd",
                    "datavalue": {
                        "value": "phyllobates-vittatus",
                        "type": "string"
                    },
                    "datatype": "external-id"
                },
                "type": "statement",
                "id": "Q1519617$1522433D-1AF0-430A-935D-5C5113B5760A",
                "rank": "normal"
            }
        ],
        "P3151": [
            {
                "mainsnak": {
                    "snaktype": "value",
                    "property": "P3151",
                    "hash": "290c08f50f5d94ed70ebf1b36b130f6a23a461be",
                    "datavalue": {
                        "value": "21214",
                        "type": "string"
                    },
                    "datatype": "external-id"
                },
                "type": "statement",
                "id": "Q1519617$97F6D958-C72C-48A7-8186-ADFDD433FCF1",
                "rank": "normal"
            }
        ],
        "P4024": [
            {
                "mainsnak": {
                    "snaktype": "value",
                    "property": "P4024",
                    "hash": "fd6c2f0e2fb2edced12ade31aa228da1b10c60f1",
                    "datavalue": {
                        "value": "Phyllobates_vittatus",
                        "type": "string"
                    },
                    "datatype": "external-id"
                },
                "type": "statement",
                "id": "Q1519617$2703A799-D7CB-4A75-AE89-3CC417D6515B",
                "rank": "normal",
                "references": [
                    {
                        "hash": "d4bd87b862b12d99d26e86472d44f26858dee639",
                        "snaks": {
                            "P143": [
                                {
                                    "snaktype": "value",
                                    "property": "P143",
                                    "hash": "f30cbd35620c4ea6d0633aaf0210a8916130469b",
                                    "datavalue": {
                                        "value": {
                                            "entity-type": "item",
                                            "numeric-id": 8447,
                                            "id": "Q8447"
                                        },
                                        "type": "wikibase-entityid"
                                    },
                                    "datatype": "wikibase-item"
                                }
                            ]
                        },
                        "snaks-order": [
                            "P143"
                        ]
                    }
                ]
            }
        ],
        "P183": [
            {
                "mainsnak": {
                    "snaktype": "value",
                    "property": "P183",
                    "hash": "5dba6c678422fedfc0b29a2aa35bd9a0904d4dae",
                    "datavalue": {
                        "value": {
                            "entity-type": "item",
                            "numeric-id": 800,
                            "id": "Q800"
                        },
                        "type": "wikibase-entityid"
                    },
                    "datatype": "wikibase-item"
                },
                "type": "statement",
                "id": "Q1519617$393BD1D6-3642-48CB-836B-65979DEBC5AF",
                "rank": "normal"
            }
        ],
        "P4728": [
            {
                "mainsnak": {
                    "snaktype": "value",
                    "property": "P4728",
                    "hash": "ad1bb44177da874fb97834ec8ea411edd8ebe9b7",
                    "datavalue": {
                        "value": "4802072",
                        "type": "string"
                    },
                    "datatype": "external-id"
                },
                "type": "statement",
                "id": "Q1519617$E984639C-CD6D-4AD3-9D84-14D926521723",
                "rank": "normal",
                "references": [
                    {
                        "hash": "d4bd87b862b12d99d26e86472d44f26858dee639",
                        "snaks": {
                            "P143": [
                                {
                                    "snaktype": "value",
                                    "property": "P143",
                                    "hash": "f30cbd35620c4ea6d0633aaf0210a8916130469b",
                                    "datavalue": {
                                        "value": {
                                            "entity-type": "item",
                                            "numeric-id": 8447,
                                            "id": "Q8447"
                                        },
                                        "type": "wikibase-entityid"
                                    },
                                    "datatype": "wikibase-item"
                                }
                            ]
                        },
                        "snaks-order": [
                            "P143"
                        ]
                    }
                ]
            }
        ],
        "P5036": [
            {
                "mainsnak": {
                    "snaktype": "value",
                    "property": "P5036",
                    "hash": "263c36e455d114b081bbf83e649836543c183708",
                    "datavalue": {
                        "value": "1708",
                        "type": "string"
                    },
                    "datatype": "external-id"
                },
                "type": "statement",
                "id": "Q1519617$014C0A24-A115-473D-96BD-6B2D0853C5E4",
                "rank": "normal",
                "references": [
                    {
                        "hash": "e4d70e1643183b7d23b6cc92133d4787b08db920",
                        "snaks": {
                            "P248": [
                                {
                                    "snaktype": "value",
                                    "property": "P248",
                                    "hash": "6031dee96aa2605fe78b65ce5c9aa8dc4ee4ef26",
                                    "datavalue": {
                                        "value": {
                                            "entity-type": "item",
                                            "numeric-id": 47263042,
                                            "id": "Q47263042"
                                        },
                                        "type": "wikibase-entityid"
                                    },
                                    "datatype": "wikibase-item"
                                }
                            ],
                            "P813": [
                                {
                                    "snaktype": "value",
                                    "property": "P813",
                                    "hash": "7d6ab927dc8e4393c2c5cc073bd0b51258de51f8",
                                    "datavalue": {
                                        "value": {
                                            "time": "+2018-04-11T00:00:00Z",
                                            "timezone": 0,
                                            "before": 0,
                                            "after": 0,
                                            "precision": 11,
                                            "calendarmodel": "http://www.wikidata.org/entity/Q1985727"
                                        },
                                        "type": "time"
                                    },
                                    "datatype": "time"
                                }
                            ]
                        },
                        "snaks-order": [
                            "P248",
                            "P813"
                        ]
                    }
                ]
            }
        ],
        "P5055": [
            {
                "mainsnak": {
                    "snaktype": "value",
                    "property": "P5055",
                    "hash": "9c76027ba9b53bc0e9aa9ce55efbd08d5cb3f1f2",
                    "datavalue": {
                        "value": "10910515",
                        "type": "string"
                    },
                    "datatype": "external-id"
                },
                "type": "statement",
                "id": "Q1519617$25141589-CFA2-4C5E-B804-FB30BD952893",
                "rank": "normal",
                "references": [
                    {
                        "hash": "936978b567ffb40d6b715a9ddbfaebde9d8e8bb1",
                        "snaks": {
                            "P248": [
                                {
                                    "snaktype": "value",
                                    "property": "P248",
                                    "hash": "1e3ad3cb9e0170e28b7c7c335fba55cafa6ef789",
                                    "datavalue": {
                                        "value": {
                                            "entity-type": "item",
                                            "numeric-id": 51885189,
                                            "id": "Q51885189"
                                        },
                                        "type": "wikibase-entityid"
                                    },
                                    "datatype": "wikibase-item"
                                }
                            ],
                            "P813": [
                                {
                                    "snaktype": "value",
                                    "property": "P813",
                                    "hash": "e948678640f83e6902fd727190bbd6b857df397a",
                                    "datavalue": {
                                        "value": {
                                            "time": "+2018-06-09T00:00:00Z",
                                            "timezone": 0,
                                            "before": 0,
                                            "after": 0,
                                            "precision": 11,
                                            "calendarmodel": "http://www.wikidata.org/entity/Q1985727"
                                        },
                                        "type": "time"
                                    },
                                    "datatype": "time"
                                }
                            ]
                        },
                        "snaks-order": [
                            "P248",
                            "P813"
                        ]
                    }
                ]
            }
        ],
        "P910": [
            {
                "mainsnak": {
                    "snaktype": "value",
                    "property": "P910",
                    "hash": "c6ea352f8e4a06b1687c32e18fd3b143e84ae3b7",
                    "datavalue": {
                        "value": {
                            "entity-type": "item",
                            "numeric-id": 55254357,
                            "id": "Q55254357"
                        },
                        "type": "wikibase-entityid"
                    },
                    "datatype": "wikibase-item"
                },
                "type": "statement",
                "id": "Q1519617$C69EB22C-55AD-453C-9DAF-C0BD160CBB01",
                "rank": "normal"
            }
        ],
        "P6018": [
            {
                "mainsnak": {
                    "snaktype": "value",
                    "property": "P6018",
                    "hash": "d3684020e969829a5e80cbeea0a0043d0785bbea",
                    "datavalue": {
                        "value": "62305",
                        "type": "string"
                    },
                    "datatype": "external-id"
                },
                "type": "statement",
                "id": "Q1519617$2B34F303-65BE-46B7-915D-C79BDF4857A8",
                "rank": "normal",
                "references": [
                    {
                        "hash": "ceccfdac147766e16ab81fd97d71115527f6a06a",
                        "snaks": {
                            "P248": [
                                {
                                    "snaktype": "value",
                                    "property": "P248",
                                    "hash": "18d34877fb9f20376e5e75a04e448143bc7fa4d8",
                                    "datavalue": {
                                        "value": {
                                            "entity-type": "item",
                                            "numeric-id": 7439813,
                                            "id": "Q7439813"
                                        },
                                        "type": "wikibase-entityid"
                                    },
                                    "datatype": "wikibase-item"
                                }
                            ],
                            "P813": [
                                {
                                    "snaktype": "value",
                                    "property": "P813",
                                    "hash": "8f896a71d465c977998a14a0fb231931f81a8148",
                                    "datavalue": {
                                        "value": {
                                            "time": "+2018-11-20T00:00:00Z",
                                            "timezone": 0,
                                            "before": 0,
                                            "after": 0,
                                            "precision": 11,
                                            "calendarmodel": "http://www.wikidata.org/entity/Q1985727"
                                        },
                                        "type": "time"
                                    },
                                    "datatype": "time"
                                }
                            ]
                        },
                        "snaks-order": [
                            "P248",
                            "P813"
                        ]
                    }
                ]
            }
        ],
        "P6105": [
            {
                "mainsnak": {
                    "snaktype": "value",
                    "property": "P6105",
                    "hash": "d5abbd50f0001ef9e3dc853245ca8748a7b7c18c",
                    "datavalue": {
                        "value": "186684",
                        "type": "string"
                    },
                    "datatype": "external-id"
                },
                "type": "statement",
                "id": "Q1519617$7975A365-5524-4CDB-B775-68D848145645",
                "rank": "normal"
            }
        ]
    },
    "sitelinks": {
        "cebwiki": {
            "site": "cebwiki",
            "title": "Phyllobates vittatus",
            "badges": []
        },
        "commonswiki": {
            "site": "commonswiki",
            "title": "Phyllobates vittatus",
            "badges": []
        },
        "dewiki": {
            "site": "dewiki",
            "title": "Gestreifter Blattsteiger",
            "badges": []
        },
        "enwiki": {
            "site": "enwiki",
            "title": "Golfodulcean poison frog",
            "badges": []
        },
        "eswiki": {
            "site": "eswiki",
            "title": "Phyllobates vittatus",
            "badges": []
        },
        "euwiki": {
            "site": "euwiki",
            "title": "Phyllobates vittatus",
            "badges": []
        },
        "fiwiki": {
            "site": "fiwiki",
            "title": "Golfodulcenmyrkkysammakko",
            "badges": []
        },
        "frwiki": {
            "site": "frwiki",
            "title": "Phyllobates vittatus",
            "badges": [
                "Q17437798"
            ]
        },
        "nlwiki": {
            "site": "nlwiki",
            "title": "Gestreepte pijlgifkikker",
            "badges": []
        },
        "nvwiki": {
            "site": "nvwiki",
            "title": "Chʼał kʼaasdáhí bijáád yistłʼinígíí",
            "badges": []
        },
        "plwiki": {
            "site": "plwiki",
            "title": "Liściołaz paskowany",
            "badges": []
        },
        "ruwiki": {
            "site": "ruwiki",
            "title": "Полосатый листолаз",
            "badges": []
        },
        "specieswiki": {
            "site": "specieswiki",
            "title": "Phyllobates vittatus",
            "badges": []
        },
        "svwiki": {
            "site": "svwiki",
            "title": "Phyllobates vittatus",
            "badges": []
        },
        "viwiki": {
            "site": "viwiki",
            "title": "Phyllobates vittatus",
            "badges": []
        },
        "warwiki": {
            "site": "warwiki",
            "title": "Phyllobates vittatus",
            "badges": []
        }
    }
}